pyloggers/__init__.py
tests/__init__.py
tests/test_pyloggers.py
tests/pkg/__init__.py
tests/pkg/subpkg/__init__.py
tests/pkg/subpkg/test_pyloggers.py
pyloggers-0.3.dist-info/METADATA
pyloggers-0.3.dist-info/WHEEL
pyloggers-0.3.dist-info/top_level.txt
pyloggers-0.3.dist-info/RECORD
