Metadata-Version: 2.1
Name: pyloggers
Version: 0.3
Summary: loggers for Python2&3
Home-page: https://github.com/hezhiming/pyloggers
Author: he.zhiming
Author-email: he.zhiming@foxmail.com
License: UNKNOWN
Platform: UNKNOWN
Classifier: Programming Language :: Python :: 2.7
Classifier: Programming Language :: Python :: 3
Classifier: License :: OSI Approved :: MIT License
Classifier: Intended Audience :: Developers
Classifier: Programming Language :: Python :: Implementation :: CPython
Classifier: Programming Language :: Python :: Implementation :: PyPy
